Workbook

Sheet 📊 Resumen Ejecutivo
B2: PLAN DE PAUTA DIGITAL — RESUMEN EJECUTIVO
B3: Campaña de 15 días | Todos los canales: Instagram · Facebook · Google Youtube · Google Display
B5: ⚙ PARÁMETROS DE CAMPAÑA (edite los valores en amarillo)
B6: Presupuesto total campaña (COP) | E6: 44875000
B7: Duración (días) | E7: 15
B8: % Meta | E8: 0.38
B9: % Pilas | E9: 0.32
B10: % Youtube | E10: 0.07
B11: % Google Display | E11: 0.23
B12: CPM estimado Meta (COP) | E12: 6750
B13: CPM estimado Pilas (COP) | E13: 6750
B14: CPM estimado Youtube (COP) | E14: 7000
B15: CPM estimado Google Display (COP) | E15: 3500
B16: CTR estimado Meta (%) | E16: 0.017
B17: CTR estimado Pilas (%) | E17: 0.017
... B19: CTR estimado Google Display (%) | E19: 0.008
B22: 📈 KPIs PROYECTADOS TOTALES
B23: Inversión Total (COP) | C23: Impresiones Totales | D23: Clicks Totales | E23: CTR Promedio Ponderado | F23: Costo por Click (COP) | G23: Duración (días)
B24: ='📊 Resumen Ejecutivo'!E6 -> 44875000 | C24: =('📊 Resumen Ejecutivo'!E6*'📊 Resumen Ejecutivo'!E8/('📊 Resumen Ejecutivo'!E12/1000))+('📊 Resumen Ejecutivo'!E6*'📊 Resumen Ejecutivo'!E9/('📊 Resumen Ejecutivo'!E13/1000))+('📊 Resumen Ejecutivo'!E6*'📊 Resumen Ejecutivo'!E10/('📊 Resumen Ejecutivo'!E14/1000))+('📊 Resumen Ejecutivo'!E6*'📊 Resumen Ejecutivo'!E11/('📊 Resumen Ejecutivo'!E15/1000)) -> 8051382.3 | D24: =(C24*E24) -> 152895.75 | E24: =('📊 Resumen Ejecutivo'!$E$8*'📊 Resumen Ejecutivo'!$E$16+'📊 Resumen Ejecutivo'!$E$9*'📊 Resumen Ejecutivo'!$E$17+'📊 Resumen Ejecutivo'!$E$10*'📊 Resumen Ejecutivo'!$E$18+'📊 Resumen Ejecutivo'!$E$11*'📊 Resumen Ejecutivo'!$E$19)/('📊 Resumen Ejecutivo'!$E$8+'📊 Resumen Ejecutivo'!$E$9+'📊 Resumen Ejecutivo'!$E$10+'📊 Resumen Ejecutivo'!$E$11) -> 0.01899 | F24: =IF(D24>0,B24/D24,0) -> 293.50064 | G24: ='📊 Resumen Ejecutivo'!E7 -> 15
B26: 🎯 SEGUIMIENTO REAL vs META (actualice columna 'Real' durante la campaña)
B27: Canal | C27: Inversión Meta (COP) | D27: Inversión Real (COP) | E27: Diferencia (COP) | F27: % Ejecución | G27: Impresiones Meta | H27: Clicks Meta
B28: Meta | C28: ='📊 Resumen Ejecutivo'!E6*'📊 Resumen Ejecutivo'!E8 -> 17052500 | D28: 0 | E28: =D28-C28 -> -17052500 | F28: =IF(C28>0,D28/C28,0) -> 0 | G28: ='📊 Resumen Ejecutivo'!E6*'📊 Resumen Ejecutivo'!E8/('📊 Resumen Ejecutivo'!E12/1000) -> 2526296.3 | H28: ='📊 Resumen Ejecutivo'!E6*'📊 Resumen Ejecutivo'!E8/('📊 Resumen Ejecutivo'!E12/1000)*'📊 Resumen Ejecutivo'!E16 -> 42947.037
B29: Pilas | C29: ='📊 Resumen Ejecutivo'!E6*'📊 Resumen Ejecutivo'!E9 -> 14360000 | D29: 0 | E29: =D29-C29 -> -14360000 | F29: =IF(C29>0,D29/C29,0) -> 0 | G29: ='📊 Resumen Ejecutivo'!E6*'📊 Resumen Ejecutivo'!E9/('📊 Resumen Ejecutivo'!E13/1000) -> 2127407.4 | H29: ='📊 Resumen Ejecutivo'!E6*'📊 Resumen Ejecutivo'!E9/('📊 Resumen Ejecutivo'!E13/1000)*'📊 Resumen Ejecutivo'!E17 -> 36165.926
B30: Youtube | C30: ='📊 Resumen Ejecutivo'!E6*'📊 Resumen Ejecutivo'!E10 -> 3141250 | D30: 0 | E30: =D30-C30 -> -3141250 | F30: =IF(C30>0,D30/C30,0) -> 0 | G30: ='📊 Resumen Ejecutivo'!E6*'📊 Resumen Ejecutivo'!E10/('📊 Resumen Ejecutivo'!E14/1000) -> 448750 | H30: ='📊 Resumen Ejecutivo'!E6*'📊 Resumen Ejecutivo'!E10/('📊 Resumen Ejecutivo'!E14/1000)*'📊 Resumen Ejecutivo'!E18 -> 33656.25
B31: Google Display | C31: ='📊 Resumen Ejecutivo'!E6*'📊 Resumen Ejecutivo'!E11 -> 10321250 | D31: 0 | E31: =D31-C31 -> -10321250 | F31: =IF(C31>0,D31/C31,0) -> 0 | G31: ='📊 Resumen Ejecutivo'!E6*'📊 Resumen Ejecutivo'!E11/('📊 Resumen Ejecutivo'!E15/1000) -> 2948928.6 | H31: ='📊 Resumen Ejecutivo'!E6*'📊 Resumen Ejecutivo'!E11/('📊 Resumen Ejecutivo'!E15/1000)*'📊 Resumen Ejecutivo'!E19 -> 23591.429
B32: TOTAL CAMPAÑA | C32: =SUM(C28:C31) -> 44875000 | D32: =SUM(D28:D31) -> 0 | E32: =SUM(E28:E31) -> -44875000 | F32: =IF(C32>0,D32/C32,0) -> 0 | G32: =SUM(G28:G31) -> 8051382.3 | H32: =SUM(H28:H31) -> 136360.64
B34: * Celdas en amarillo son editables. Actualice 'Inversión Real' diariamente para monitorear la ejecución presupuestal.

Sheet 📣 Distribución x Canal
B2: DISTRIBUCIÓN PRESUPUESTARIA POR CANAL — 15 DÍAS
B3: Los porcentajes en amarillo son editables. Las fórmulas se actualizan automáticamente.
B5: Canal | C5: % Participación | D5: Presupuesto Total (COP) | E5: Presupuesto Diario (COP) | F5: CPM (COP) | G5: Impresiones Totales | H5: CTR Estimado | I5: Clicks Totales | J5: CPC Estimado (COP) | K5: Alcance Estimado
B6: Meta | C6: ='📊 Resumen Ejecutivo'!E8 -> 0.38 | D6: ='📊 Resumen Ejecutivo'!$E$6*C6 -> 17052500 | E6: =D6/'📊 Resumen Ejecutivo'!$E$7 -> 1136833.3 | F6: ='📊 Resumen Ejecutivo'!E12 -> 6750 | G6: =(D6/(F6/1000)) -> 2526296.3 | H6: ='📊 Resumen Ejecutivo'!E16 -> 0.017 | I6: =G6*H6 -> 42947.037 | J6: =IF(I6>0,D6/I6,0) -> 397.05882 | K6: =G6*0.7 -> 1768407.4
B7: Pilas | C7: ='📊 Resumen Ejecutivo'!E9 -> 0.32 | D7: ='📊 Resumen Ejecutivo'!$E$6*C7 -> 14360000 | E7: =D7/'📊 Resumen Ejecutivo'!$E$7 -> 957333.33 | F7: ='📊 Resumen Ejecutivo'!E13 -> 6750 | G7: =(D7/(F7/1000)) -> 2127407.4 | H7: ='📊 Resumen Ejecutivo'!E17 -> 0.017 | I7: =G7*H7 -> 36165.926 | J7: =IF(I7>0,D7/I7,0) -> 397.05882 | K7: =G7*0.7 -> 1489185.2
B8: Youtube | C8: ='📊 Resumen Ejecutivo'!E10 -> 0.07 | D8: ='📊 Resumen Ejecutivo'!$E$6*C8 -> 3141250 | E8: =D8/'📊 Resumen Ejecutivo'!$E$7 -> 209416.67 | F8: ='📊 Resumen Ejecutivo'!E14 -> 7000 | G8: =(D8/(F8/1000)) -> 448750 | H8: ='📊 Resumen Ejecutivo'!E18 -> 0.075 | I8: =G8*H8 -> 33656.25 | J8: =IF(I8>0,D8/I8,0) -> 93.333333 | K8: =G8*0.7 -> 314125
B9: Google Display | C9: ='📊 Resumen Ejecutivo'!E11 -> 0.23 | D9: ='📊 Resumen Ejecutivo'!$E$6*C9 -> 10321250 | E9: =D9/'📊 Resumen Ejecutivo'!$E$7 -> 688083.33 | F9: ='📊 Resumen Ejecutivo'!E15 -> 3500 | G9: =(D9/(F9/1000)) -> 2948928.6 | H9: ='📊 Resumen Ejecutivo'!E19 -> 0.008 | I9: =G9*H9 -> 23591.429 | J9: =IF(I9>0,D9/I9,0) -> 437.5 | K9: =G9*0.7 -> 2064250
B10: TOTAL | C10: =SUM(C6:C9) -> 1 | D10: =SUM(D6:D9) -> 44875000 | E10: =SUM(E6:E9) -> 2991666.7 | F10: =SUMPRODUCT(C6:C9,F6:F9)/SUM(C6:C9) -> 6020 | G10: =SUM(G6:G9) -> 8051382.3 | H10: =SUMPRODUCT(C6:C9,H6:H9)/SUM(C6:C9) -> 0.01899 | I10: =SUM(I6:I9) -> 136360.64 | J10: =SUM(J6:J9) -> 1324.951 | K10: =SUM(K6:K9) -> 5635967.6
B13: 📌 OBJETIVOS Y TIPO DE CAMPAÑA POR CANAL
B14: Canal | C14: Objetivo Principal | D14: Formato Recomendado | E14: Público Objetivo | K14: KPI Principal
B15: Meta | C15: Reconocimiento de marca y engagement | E15: Segmentación por intereses Demografía 18–45 años | K15: Alcance + Engagement Rate
B16: Pilas | C16: Tráfico al sitio web y generación de leads | E16: Lookalike audiences Remarketing | K16: CPC + CTR + Leads
B17: Youtube | C17: Captura de demanda activa / intención de búsqueda | E17: Keywords relacionadas a nombre y propuesta | K17: CTR + CPC + Conversiones
B18: Google Display | C18: Cobertura y retargeting visual | E18: Retargeting web + audiencias en mercado | K18: CPM + Frecuencia + Viewability
B20: * Alcance estimado usa factor de frecuencia 1.4x (cada usuario ve el anuncio ~1.4 veces en promedio)

Sheet 📅 Desglose Diario
B2: DESGLOSE DIARIO DE INVERSIÓN — 15 DÍAS
B3: Inversión diaria distribuida por canal. Ajuste los pesos en la columna 'Factor' para modificar la distribución por día.
B5: Día | C5: Fecha (inicio: edite) | D5: Factor Peso (editable) | E5: Inversión Total/Día (COP) | F5: Meta (COP) | G5: Pilas(COP) | H5: Youtube (COP) | I5: Google Display (COP) | J5: Imp. MT | K5: Imp. PL | L5: Imp. YT | M5: Imp. GD
B6: 1 | C6: 46182 | D6: 0.7 | E6: ='📊 Resumen Ejecutivo'!$E$6*(D6/SUM($D$6:$D$20)) -> 1697973 | F6: =E6*'📊 Resumen Ejecutivo'!$E$8 -> 645229.73 | G6: =E6*'📊 Resumen Ejecutivo'!$E$9 -> 543351.35 | H6: =E6*'📊 Resumen Ejecutivo'!$E$10 -> 118858.11 | I6: =E6*'📊 Resumen Ejecutivo'!$E$11 -> 390533.78 | J6: =(F6/('📊 Resumen Ejecutivo'!$E$12/1000)) -> 95589.59 | K6: =(G6/('📊 Resumen Ejecutivo'!$E$13/1000)) -> 80496.496 | L6: =(H6/('📊 Resumen Ejecutivo'!$E$14/1000)) -> 16979.73 | M6: =(I6/('📊 Resumen Ejecutivo'!$E$15/1000)) -> 111581.08
B7: 2 | C7: =C6+1 -> 46183 | D7: 0.8 | E7: ='📊 Resumen Ejecutivo'!$E$6*(D7/SUM($D$6:$D$20)) -> 1940540.5 | F7: =E7*'📊 Resumen Ejecutivo'!$E$8 -> 737405.41 | G7: =E7*'📊 Resumen Ejecutivo'!$E$9 -> 620972.97 | H7: =E7*'📊 Resumen Ejecutivo'!$E$10 -> 135837.84 | I7: =E7*'📊 Resumen Ejecutivo'!$E$11 -> 446324.32 | J7: =(F7/('📊 Resumen Ejecutivo'!$E$12/1000)) -> 109245.25 | K7: =(G7/('📊 Resumen Ejecutivo'!$E$13/1000)) -> 91995.996 | L7: =(H7/('📊 Resumen Ejecutivo'!$E$14/1000)) -> 19405.405 | M7: =(I7/('📊 Resumen Ejecutivo'!$E$15/1000)) -> 127521.24
B8: 3 | C8: =C7+1 -> 46184 | D8: 0.9 | E8: ='📊 Resumen Ejecutivo'!$E$6*(D8/SUM($D$6:$D$20)) -> 2183108.1 | F8: =E8*'📊 Resumen Ejecutivo'!$E$8 -> 829581.08 | G8: =E8*'📊 Resumen Ejecutivo'!$E$9 -> 698594.59 | H8: =E8*'📊 Resumen Ejecutivo'!$E$10 -> 152817.57 | I8: =E8*'📊 Resumen Ejecutivo'!$E$11 -> 502114.86 | J8: =(F8/('📊 Resumen Ejecutivo'!$E$12/1000)) -> 122900.9 | K8: =(G8/('📊 Resumen Ejecutivo'!$E$13/1000)) -> 103495.5 | L8: =(H8/('📊 Resumen Ejecutivo'!$E$14/1000)) -> 21831.081 | M8: =(I8/('📊 Resumen Ejecutivo'!$E$15/1000)) -> 143461.39
B9: 4 | C9: =C8+1 -> 46185 | D9: 1 | E9: ='📊 Resumen Ejecutivo'!$E$6*(D9/SUM($D$6:$D$20)) -> 2425675.7 | F9: =E9*'📊 Resumen Ejecutivo'!$E$8 -> 921756.76 | G9: =E9*'📊 Resumen Ejecutivo'!$E$9 -> 776216.22 | H9: =E9*'📊 Resumen Ejecutivo'!$E$10 -> 169797.3 | I9: =E9*'📊 Resumen Ejecutivo'!$E$11 -> 557905.41 | J9: =(F9/('📊 Resumen Ejecutivo'!$E$12/1000)) -> 136556.56 | K9: =(G9/('📊 Resumen Ejecutivo'!$E$13/1000)) -> 114994.99 | L9: =(H9/('📊 Resumen Ejecutivo'!$E$14/1000)) -> 24256.757 | M9: =(I9/('📊 Resumen Ejecutivo'!$E$15/1000)) -> 159401.54
B10: 5 | C10: =C9+1 -> 46186 | D10: 1.05 | E10: ='📊 Resumen Ejecutivo'!$E$6*(D10/SUM($D$6:$D$20)) -> 2546959.5 | F10: =E10*'📊 Resumen Ejecutivo'!$E$8 -> 967844.59 | G10: =E10*'📊 Resumen Ejecutivo'!$E$9 -> 815027.03 | H10: =E10*'📊 Resumen Ejecutivo'!$E$10 -> 178287.16 | I10: =E10*'📊 Resumen Ejecutivo'!$E$11 -> 585800.68 | J10: =(F10/('📊 Resumen Ejecutivo'!$E$12/1000)) -> 143384.38 | K10: =(G10/('📊 Resumen Ejecutivo'!$E$13/1000)) -> 120744.74 | L10: =(H10/('📊 Resumen Ejecutivo'!$E$14/1000)) -> 25469.595 | M10: =(I10/('📊 Resumen Ejecutivo'!$E$15/1000)) -> 167371.62
B11: 6 | C11: =C10+1 -> 46187 | D11: 1.1 | E11: ='📊 Resumen Ejecutivo'!$E$6*(D11/SUM($D$6:$D$20)) -> 2668243.2 | F11: =E11*'📊 Resumen Ejecutivo'!$E$8 -> 1013932.4 | G11: =E11*'📊 Resumen Ejecutivo'!$E$9 -> 853837.84 | H11: =E11*'📊 Resumen Ejecutivo'!$E$10 -> 186777.03 | I11: =E11*'📊 Resumen Ejecutivo'!$E$11 -> 613695.95 | J11: =(F11/('📊 Resumen Ejecutivo'!$E$12/1000)) -> 150212.21 | K11: =(G11/('📊 Resumen Ejecutivo'!$E$13/1000)) -> 126494.49 | L11: =(H11/('📊 Resumen Ejecutivo'!$E$14/1000)) -> 26682.432 | M11: =(I11/('📊 Resumen Ejecutivo'!$E$15/1000)) -> 175341.7
B12: 7 | C12: =C11+1 -> 46188 | D12: 1.2 | E12: ='📊 Resumen Ejecutivo'!$E$6*(D12/SUM($D$6:$D$20)) -> 2910810.8 | F12: =E12*'📊 Resumen Ejecutivo'!$E$8 -> 1106108.1 | G12: =E12*'📊 Resumen Ejecutivo'!$E$9 -> 931459.46 | H12: =E12*'📊 Resumen Ejecutivo'!$E$10 -> 203756.76 | I12: =E12*'📊 Resumen Ejecutivo'!$E$11 -> 669486.49 | J12: =(F12/('📊 Resumen Ejecutivo'!$E$12/1000)) -> 163867.87 | K12: =(G12/('📊 Resumen Ejecutivo'!$E$13/1000)) -> 137993.99 | L12: =(H12/('📊 Resumen Ejecutivo'!$E$14/1000)) -> 29108.108 | M12: =(I12/('📊 Resumen Ejecutivo'!$E$15/1000)) -> 191281.85
B13: 8 | C13: =C12+1 -> 46189 | D13: 1.2 | E13: ='📊 Resumen Ejecutivo'!$E$6*(D13/SUM($D$6:$D$20)) -> 2910810.8 | F13: =E13*'📊 Resumen Ejecutivo'!$E$8 -> 1106108.1 | G13: =E13*'📊 Resumen Ejecutivo'!$E$9 -> 931459.46 | H13: =E13*'📊 Resumen Ejecutivo'!$E$10 -> 203756.76 | I13: =E13*'📊 Resumen Ejecutivo'!$E$11 -> 669486.49 | J13: =(F13/('📊 Resumen Ejecutivo'!$E$12/1000)) -> 163867.87 | K13: =(G13/('📊 Resumen Ejecutivo'!$E$13/1000)) -> 137993.99 | L13: =(H13/('📊 Resumen Ejecutivo'!$E$14/1000)) -> 29108.108 | M13: =(I13/('📊 Resumen Ejecutivo'!$E$15/1000)) -> 191281.85
B14: 9 | C14: =C13+1 -> 46190 | D14: 1.1 | E14: ='📊 Resumen Ejecutivo'!$E$6*(D14/SUM($D$6:$D$20)) -> 2668243.2 | F14: =E14*'📊 Resumen Ejecutivo'!$E$8 -> 1013932.4 | G14: =E14*'📊 Resumen Ejecutivo'!$E$9 -> 853837.84 | H14: =E14*'📊 Resumen Ejecutivo'!$E$10 -> 186777.03 | I14: =E14*'📊 Resumen Ejecutivo'!$E$11 -> 613695.95 | J14: =(F14/('📊 Resumen Ejecutivo'!$E$12/1000)) -> 150212.21 | K14: =(G14/('📊 Resumen Ejecutivo'!$E$13/1000)) -> 126494.49 | L14: =(H14/('📊 Resumen Ejecutivo'!$E$14/1000)) -> 26682.432 | M14: =(I14/('📊 Resumen Ejecutivo'!$E$15/1000)) -> 175341.7
B15: 10 | C15: =C14+1 -> 46191 | D15: 1.1 | E15: ='📊 Resumen Ejecutivo'!$E$6*(D15/SUM($D$6:$D$20)) -> 2668243.2 | F15: =E15*'📊 Resumen Ejecutivo'!$E$8 -> 1013932.4 | G15: =E15*'📊 Resumen Ejecutivo'!$E$9 -> 853837.84 | H15: =E15*'📊 Resumen Ejecutivo'!$E$10 -> 186777.03 | I15: =E15*'📊 Resumen Ejecutivo'!$E$11 -> 613695.95 | J15: =(F15/('📊 Resumen Ejecutivo'!$E$12/1000)) -> 150212.21 | K15: =(G15/('📊 Resumen Ejecutivo'!$E$13/1000)) -> 126494.49 | L15: =(H15/('📊 Resumen Ejecutivo'!$E$14/1000)) -> 26682.432 | M15: =(I15/('📊 Resumen Ejecutivo'!$E$15/1000)) -> 175341.7
B16: 11 | C16: =C15+1 -> 46192 | D16: 1.5 | E16: ='📊 Resumen Ejecutivo'!$E$6*(D16/SUM($D$6:$D$20)) -> 3638513.5 | F16: =E16*'📊 Resumen Ejecutivo'!$E$8 -> 1382635.1 | G16: =E16*'📊 Resumen Ejecutivo'!$E$9 -> 1164324.3 | H16: =E16*'📊 Resumen Ejecutivo'!$E$10 -> 254695.95 | I16: =E16*'📊 Resumen Ejecutivo'!$E$11 -> 836858.11 | J16: =(F16/('📊 Resumen Ejecutivo'!$E$12/1000)) -> 204834.83 | K16: =(G16/('📊 Resumen Ejecutivo'!$E$13/1000)) -> 172492.49 | L16: =(H16/('📊 Resumen Ejecutivo'!$E$14/1000)) -> 36385.135 | M16: =(I16/('📊 Resumen Ejecutivo'!$E$15/1000)) -> 239102.32
B17: 12 | C17: =C16+1 -> 46193 | D17: 2.5 | E17: ='📊 Resumen Ejecutivo'!$E$6*(D17/SUM($D$6:$D$20)) -> 6064189.2 | F17: =E17*'📊 Resumen Ejecutivo'!$E$8 -> 2304391.9 | G17: =E17*'📊 Resumen Ejecutivo'!$E$9 -> 1940540.5 | H17: =E17*'📊 Resumen Ejecutivo'!$E$10 -> 424493.24 | I17: =E17*'📊 Resumen Ejecutivo'!$E$11 -> 1394763.5 | J17: =(F17/('📊 Resumen Ejecutivo'!$E$12/1000)) -> 341391.39 | K17: =(G17/('📊 Resumen Ejecutivo'!$E$13/1000)) -> 287487.49 | L17: =(H17/('📊 Resumen Ejecutivo'!$E$14/1000)) -> 60641.892 | M17: =(I17/('📊 Resumen Ejecutivo'!$E$15/1000)) -> 398503.86
B18: 13 | C18: =C17+1 -> 46194 | D18: 2.5 | E18: ='📊 Resumen Ejecutivo'!$E$6*(D18/SUM($D$6:$D$20)) -> 6064189.2 | F18: =E18*'📊 Resumen Ejecutivo'!$E$8 -> 2304391.9 | G18: =E18*'📊 Resumen Ejecutivo'!$E$9 -> 1940540.5 | H18: =E18*'📊 Resumen Ejecutivo'!$E$10 -> 424493.24 | I18: =E18*'📊 Resumen Ejecutivo'!$E$11 -> 1394763.5 | J18: =(F18/('📊 Resumen Ejecutivo'!$E$12/1000)) -> 341391.39 | K18: =(G18/('📊 Resumen Ejecutivo'!$E$13/1000)) -> 287487.49 | L18: =(H18/('📊 Resumen Ejecutivo'!$E$14/1000)) -> 60641.892 | M18: =(I18/('📊 Resumen Ejecutivo'!$E$15/1000)) -> 398503.86
... B20: 15 | C20: =C19+1 -> 46196 | D20: 0.7 | E20: ='📊 Resumen Ejecutivo'!$E$6*(D20/SUM($D$6:$D$20)) -> 1697973 | F20: =E20*'📊 Resumen Ejecutivo'!$E$8 -> 645229.73 | G20: =E20*'📊 Resumen Ejecutivo'!$E$9 -> 543351.35 | H20: =E20*'📊 Resumen Ejecutivo'!$E$10 -> 118858.11 | I20: =E20*'📊 Resumen Ejecutivo'!$E$11 -> 390533.78 | J20: =(F20/('📊 Resumen Ejecutivo'!$E$12/1000)) -> 95589.59 | K20: =(G20/('📊 Resumen Ejecutivo'!$E$13/1000)) -> 80496.496 | L20: =(H20/('📊 Resumen Ejecutivo'!$E$14/1000)) -> 16979.73 | M20: =(I20/('📊 Resumen Ejecutivo'!$E$15/1000)) -> 111581.08
B21: TOTAL | C21: 15 días | D21: =SUM(D6:D20) -> 18.5 | E21: =SUM(E6:E20) -> 44875000 | F21: =SUM(F6:F20) -> 17052500 | G21: =SUM(G6:G20) -> 14360000 | H21: =SUM(H6:H20) -> 3141250 | I21: =SUM(I6:I20) -> 10321250 | J21: =SUM(J6:J20) -> 2526296.3 | K21: =SUM(K6:K20) -> 2127407.4 | ... M21: =SUM(M6:M20) -> 2948928.6
B23: * Edite 'Factor Peso' de cada día para redistribuir la inversión. El total siempre suma el presupuesto total sin importar los factores.
B24: * Fecha inicio: edite la celda C6 para ajustar el calendario completo.

Sheet 📈 Proyecciones
A1: 8xde
B2: PROYECCIONES DE IMPRESIONES Y CLICKS — 15 DÍAS
B3: Proyecciones basadas en parámetros del Resumen Ejecutivo. Todos los valores se actualizan al cambiar CPM o CTR.
B5: PROYECCIÓN CONSOLIDADA POR CANAL
B6: Canal | C6: Inversión Total (COP) | D6: CPM (COP) | E6: Impresiones Totales | F6: CTR | G6: Clicks Totales | H6: CPC (COP) | I6: Frecuencia Estimada | J6: Alcance Único Est.
B7: Meta | C7: ='📊 Resumen Ejecutivo'!$E$6*'📊 Resumen Ejecutivo'!$E$8 -> 17052500 | D7: ='📊 Resumen Ejecutivo'!$E$12 -> 6750 | E7: =(C7/(D7/1000)) -> 2526296.3 | F7: ='📊 Resumen Ejecutivo'!$E$16 -> 0.017 | G7: =E7*F7 -> 42947.037 | H7: =IF(G7>0,C7/G7,0) -> 397.05882 | I7: 1.4 | J7: =IF(I7>0,E7/I7,0) -> 1804497.4
B8: Pilas | C8: ='📊 Resumen Ejecutivo'!$E$6*'📊 Resumen Ejecutivo'!$E$9 -> 14360000 | D8: ='📊 Resumen Ejecutivo'!$E$13 -> 6750 | E8: =(C8/(D8/1000)) -> 2127407.4 | F8: ='📊 Resumen Ejecutivo'!$E$17 -> 0.017 | G8: =E8*F8 -> 36165.926 | H8: =IF(G8>0,C8/G8,0) -> 397.05882 | I8: 1.6 | J8: =IF(I8>0,E8/I8,0) -> 1329629.6
B9: Youtube | C9: ='📊 Resumen Ejecutivo'!$E$6*'📊 Resumen Ejecutivo'!$E$10 -> 3141250 | D9: ='📊 Resumen Ejecutivo'!$E$14 -> 7000 | E9: =(C9/(D9/1000)) -> 448750 | F9: ='📊 Resumen Ejecutivo'!$E$18 -> 0.075 | G9: =E9*F9 -> 33656.25 | H9: =IF(G9>0,C9/G9,0) -> 93.333333 | I9: 1.3 | J9: =IF(I9>0,E9/I9,0) -> 345192.31
B10: Google Display | C10: ='📊 Resumen Ejecutivo'!$E$6*'📊 Resumen Ejecutivo'!$E$11 -> 10321250 | D10: ='📊 Resumen Ejecutivo'!$E$15 -> 3500 | E10: =(C10/(D10/1000)) -> 2948928.6 | F10: ='📊 Resumen Ejecutivo'!$E$19 -> 0.008 | G10: =E10*F10 -> 23591.429 | H10: =IF(G10>0,C10/G10,0) -> 437.5 | I10: 2 | J10: =IF(I10>0,E10/I10,0) -> 1474464.3
B11: TOTAL | C11: =SUM(C7:C10) -> 44875000 | D11: =('📊 Resumen Ejecutivo'!$E$8*D7+'📊 Resumen Ejecutivo'!$E$9*D8+'📊 Resumen Ejecutivo'!$E$10*D9+'📊 Resumen Ejecutivo'!$E$11*D10)/('📊 Resumen Ejecutivo'!$E$8+'📊 Resumen Ejecutivo'!$E$9+'📊 Resumen Ejecutivo'!$E$10+'📊 Resumen Ejecutivo'!$E$11) -> 6020 | E11: =SUM(E7:E10) -> 8051382.3 | F11: =IF(E11>0,G11/E11,0) -> 0.016936302 | G11: =SUM(G7:G10) -> 136360.64 | H11: =IF(G11>0,C11/G11,0) -> 329.09056 | I11: — | J11: =SUM(J7:J10) -> 4953783.6
B14: PROYECCIÓN DIARIA — IMPRESIONES Y CLICKS TOTALES (todos los canales)
B15: Día | C15: Fecha | D15: Inversión/Día (COP) | E15: Imp. Meta | F15: Imp. Pilas | G15: Imp. Youtube | H15: Imp. Display | I15: Total Impresiones | J15: Total Clicks
B16: 1 | C16: ='📅 Desglose Diario'!C6 -> 46182 | D16: ='📅 Desglose Diario'!E6 -> 1697973 | E16: =('📅 Desglose Diario'!F6/('📊 Resumen Ejecutivo'!$E$12/1000)) -> 95589.59 | F16: =('📅 Desglose Diario'!G6/('📊 Resumen Ejecutivo'!$E$13/1000)) -> 80496.496 | G16: =('📅 Desglose Diario'!H6/('📊 Resumen Ejecutivo'!$E$14/1000)) -> 16979.73 | H16: =('📅 Desglose Diario'!I6/('📊 Resumen Ejecutivo'!$E$15/1000)) -> 111581.08 | I16: =SUM(E16:H16) -> 304646.9 | J16: =E16*'📊 Resumen Ejecutivo'!$E$16+F16*'📊 Resumen Ejecutivo'!$E$17+G16*'📊 Resumen Ejecutivo'!$E$18+H16*'📊 Resumen Ejecutivo'!$E$19 -> 5159.5918
B17: 2 | C17: ='📅 Desglose Diario'!C7 -> 46183 | D17: ='📅 Desglose Diario'!E7 -> 1940540.5 | E17: =('📅 Desglose Diario'!F7/('📊 Resumen Ejecutivo'!$E$12/1000)) -> 109245.25 | F17: =('📅 Desglose Diario'!G7/('📊 Resumen Ejecutivo'!$E$13/1000)) -> 91995.996 | G17: =('📅 Desglose Diario'!H7/('📊 Resumen Ejecutivo'!$E$14/1000)) -> 19405.405 | H17: =('📅 Desglose Diario'!I7/('📊 Resumen Ejecutivo'!$E$15/1000)) -> 127521.24 | I17: =SUM(E17:H17) -> 348167.88 | J17: =E17*'📊 Resumen Ejecutivo'!$E$16+F17*'📊 Resumen Ejecutivo'!$E$17+G17*'📊 Resumen Ejecutivo'!$E$18+H17*'📊 Resumen Ejecutivo'!$E$19 -> 5896.6764
B18: 3 | C18: ='📅 Desglose Diario'!C8 -> 46184 | D18: ='📅 Desglose Diario'!E8 -> 2183108.1 | E18: =('📅 Desglose Diario'!F8/('📊 Resumen Ejecutivo'!$E$12/1000)) -> 122900.9 | F18: =('📅 Desglose Diario'!G8/('📊 Resumen Ejecutivo'!$E$13/1000)) -> 103495.5 | G18: =('📅 Desglose Diario'!H8/('📊 Resumen Ejecutivo'!$E$14/1000)) -> 21831.081 | H18: =('📅 Desglose Diario'!I8/('📊 Resumen Ejecutivo'!$E$15/1000)) -> 143461.39 | I18: =SUM(E18:H18) -> 391688.87 | J18: =E18*'📊 Resumen Ejecutivo'!$E$16+F18*'📊 Resumen Ejecutivo'!$E$17+G18*'📊 Resumen Ejecutivo'!$E$18+H18*'📊 Resumen Ejecutivo'!$E$19 -> 6633.7609
B19: 4 | C19: ='📅 Desglose Diario'!C9 -> 46185 | D19: ='📅 Desglose Diario'!E9 -> 2425675.7 | E19: =('📅 Desglose Diario'!F9/('📊 Resumen Ejecutivo'!$E$12/1000)) -> 136556.56 | F19: =('📅 Desglose Diario'!G9/('📊 Resumen Ejecutivo'!$E$13/1000)) -> 114994.99 | G19: =('📅 Desglose Diario'!H9/('📊 Resumen Ejecutivo'!$E$14/1000)) -> 24256.757 | H19: =('📅 Desglose Diario'!I9/('📊 Resumen Ejecutivo'!$E$15/1000)) -> 159401.54 | I19: =SUM(E19:H19) -> 435209.85 | J19: =E19*'📊 Resumen Ejecutivo'!$E$16+F19*'📊 Resumen Ejecutivo'!$E$17+G19*'📊 Resumen Ejecutivo'!$E$18+H19*'📊 Resumen Ejecutivo'!$E$19 -> 7370.8455
B20: 5 | C20: ='📅 Desglose Diario'!C10 -> 46186 | D20: ='📅 Desglose Diario'!E10 -> 2546959.5 | E20: =('📅 Desglose Diario'!F10/('📊 Resumen Ejecutivo'!$E$12/1000)) -> 143384.38 | F20: =('📅 Desglose Diario'!G10/('📊 Resumen Ejecutivo'!$E$13/1000)) -> 120744.74 | G20: =('📅 Desglose Diario'!H10/('📊 Resumen Ejecutivo'!$E$14/1000)) -> 25469.595 | H20: =('📅 Desglose Diario'!I10/('📊 Resumen Ejecutivo'!$E$15/1000)) -> 167371.62 | I20: =SUM(E20:H20) -> 456970.35 | J20: =E20*'📊 Resumen Ejecutivo'!$E$16+F20*'📊 Resumen Ejecutivo'!$E$17+G20*'📊 Resumen Ejecutivo'!$E$18+H20*'📊 Resumen Ejecutivo'!$E$19 -> 7739.3878
B21: 6 | C21: ='📅 Desglose Diario'!C11 -> 46187 | D21: ='📅 Desglose Diario'!E11 -> 2668243.2 | E21: =('📅 Desglose Diario'!F11/('📊 Resumen Ejecutivo'!$E$12/1000)) -> 150212.21 | F21: =('📅 Desglose Diario'!G11/('📊 Resumen Ejecutivo'!$E$13/1000)) -> 126494.49 | G21: =('📅 Desglose Diario'!H11/('📊 Resumen Ejecutivo'!$E$14/1000)) -> 26682.432 | H21: =('📅 Desglose Diario'!I11/('📊 Resumen Ejecutivo'!$E$15/1000)) -> 175341.7 | I21: =SUM(E21:H21) -> 478730.84 | J21: =E21*'📊 Resumen Ejecutivo'!$E$16+F21*'📊 Resumen Ejecutivo'!$E$17+G21*'📊 Resumen Ejecutivo'!$E$18+H21*'📊 Resumen Ejecutivo'!$E$19 -> 8107.93
B22: 7 | C22: ='📅 Desglose Diario'!C12 -> 46188 | D22: ='📅 Desglose Diario'!E12 -> 2910810.8 | E22: =('📅 Desglose Diario'!F12/('📊 Resumen Ejecutivo'!$E$12/1000)) -> 163867.87 | F22: =('📅 Desglose Diario'!G12/('📊 Resumen Ejecutivo'!$E$13/1000)) -> 137993.99 | G22: =('📅 Desglose Diario'!H12/('📊 Resumen Ejecutivo'!$E$14/1000)) -> 29108.108 | H22: =('📅 Desglose Diario'!I12/('📊 Resumen Ejecutivo'!$E$15/1000)) -> 191281.85 | I22: =SUM(E22:H22) -> 522251.82 | J22: =E22*'📊 Resumen Ejecutivo'!$E$16+F22*'📊 Resumen Ejecutivo'!$E$17+G22*'📊 Resumen Ejecutivo'!$E$18+H22*'📊 Resumen Ejecutivo'!$E$19 -> 8845.0146
B23: 8 | C23: ='📅 Desglose Diario'!C13 -> 46189 | D23: ='📅 Desglose Diario'!E13 -> 2910810.8 | E23: =('📅 Desglose Diario'!F13/('📊 Resumen Ejecutivo'!$E$12/1000)) -> 163867.87 | F23: =('📅 Desglose Diario'!G13/('📊 Resumen Ejecutivo'!$E$13/1000)) -> 137993.99 | G23: =('📅 Desglose Diario'!H13/('📊 Resumen Ejecutivo'!$E$14/1000)) -> 29108.108 | H23: =('📅 Desglose Diario'!I13/('📊 Resumen Ejecutivo'!$E$15/1000)) -> 191281.85 | I23: =SUM(E23:H23) -> 522251.82 | J23: =E23*'📊 Resumen Ejecutivo'!$E$16+F23*'📊 Resumen Ejecutivo'!$E$17+G23*'📊 Resumen Ejecutivo'!$E$18+H23*'📊 Resumen Ejecutivo'!$E$19 -> 8845.0146
B24: 9 | C24: ='📅 Desglose Diario'!C14 -> 46190 | D24: ='📅 Desglose Diario'!E14 -> 2668243.2 | E24: =('📅 Desglose Diario'!F14/('📊 Resumen Ejecutivo'!$E$12/1000)) -> 150212.21 | F24: =('📅 Desglose Diario'!G14/('📊 Resumen Ejecutivo'!$E$13/1000)) -> 126494.49 | G24: =('📅 Desglose Diario'!H14/('📊 Resumen Ejecutivo'!$E$14/1000)) -> 26682.432 | H24: =('📅 Desglose Diario'!I14/('📊 Resumen Ejecutivo'!$E$15/1000)) -> 175341.7 | I24: =SUM(E24:H24) -> 478730.84 | J24: =E24*'📊 Resumen Ejecutivo'!$E$16+F24*'📊 Resumen Ejecutivo'!$E$17+G24*'📊 Resumen Ejecutivo'!$E$18+H24*'📊 Resumen Ejecutivo'!$E$19 -> 8107.93
B25: 10 | C25: ='📅 Desglose Diario'!C15 -> 46191 | D25: ='📅 Desglose Diario'!E15 -> 2668243.2 | E25: =('📅 Desglose Diario'!F15/('📊 Resumen Ejecutivo'!$E$12/1000)) -> 150212.21 | F25: =('📅 Desglose Diario'!G15/('📊 Resumen Ejecutivo'!$E$13/1000)) -> 126494.49 | G25: =('📅 Desglose Diario'!H15/('📊 Resumen Ejecutivo'!$E$14/1000)) -> 26682.432 | H25: =('📅 Desglose Diario'!I15/('📊 Resumen Ejecutivo'!$E$15/1000)) -> 175341.7 | I25: =SUM(E25:H25) -> 478730.84 | J25: =E25*'📊 Resumen Ejecutivo'!$E$16+F25*'📊 Resumen Ejecutivo'!$E$17+G25*'📊 Resumen Ejecutivo'!$E$18+H25*'📊 Resumen Ejecutivo'!$E$19 -> 8107.93
B26: 11 | C26: ='📅 Desglose Diario'!C16 -> 46192 | D26: ='📅 Desglose Diario'!E16 -> 3638513.5 | E26: =('📅 Desglose Diario'!F16/('📊 Resumen Ejecutivo'!$E$12/1000)) -> 204834.83 | F26: =('📅 Desglose Diario'!G16/('📊 Resumen Ejecutivo'!$E$13/1000)) -> 172492.49 | G26: =('📅 Desglose Diario'!H16/('📊 Resumen Ejecutivo'!$E$14/1000)) -> 36385.135 | H26: =('📅 Desglose Diario'!I16/('📊 Resumen Ejecutivo'!$E$15/1000)) -> 239102.32 | I26: =SUM(E26:H26) -> 652814.78 | J26: =E26*'📊 Resumen Ejecutivo'!$E$16+F26*'📊 Resumen Ejecutivo'!$E$17+G26*'📊 Resumen Ejecutivo'!$E$18+H26*'📊 Resumen Ejecutivo'!$E$19 -> 11056.268
B27: 12 | C27: ='📅 Desglose Diario'!C17 -> 46193 | D27: ='📅 Desglose Diario'!E17 -> 6064189.2 | E27: =('📅 Desglose Diario'!F17/('📊 Resumen Ejecutivo'!$E$12/1000)) -> 341391.39 | F27: =('📅 Desglose Diario'!G17/('📊 Resumen Ejecutivo'!$E$13/1000)) -> 287487.49 | G27: =('📅 Desglose Diario'!H17/('📊 Resumen Ejecutivo'!$E$14/1000)) -> 60641.892 | H27: =('📅 Desglose Diario'!I17/('📊 Resumen Ejecutivo'!$E$15/1000)) -> 398503.86 | I27: =SUM(E27:H27) -> 1088024.6 | J27: =E27*'📊 Resumen Ejecutivo'!$E$16+F27*'📊 Resumen Ejecutivo'!$E$17+G27*'📊 Resumen Ejecutivo'!$E$18+H27*'📊 Resumen Ejecutivo'!$E$19 -> 18427.114
... B30: 15 | C30: ='📅 Desglose Diario'!C20 -> 46196 | D30: ='📅 Desglose Diario'!E20 -> 1697973 | E30: =('📅 Desglose Diario'!F20/('📊 Resumen Ejecutivo'!$E$12/1000)) -> 95589.59 | F30: =('📅 Desglose Diario'!G20/('📊 Resumen Ejecutivo'!$E$13/1000)) -> 80496.496 | G30: =('📅 Desglose Diario'!H20/('📊 Resumen Ejecutivo'!$E$14/1000)) -> 16979.73 | H30: =('📅 Desglose Diario'!I20/('📊 Resumen Ejecutivo'!$E$15/1000)) -> 111581.08 | I30: =SUM(E30:H30) -> 304646.9 | J30: =E30*'📊 Resumen Ejecutivo'!$E$16+F30*'📊 Resumen Ejecutivo'!$E$17+G30*'📊 Resumen Ejecutivo'!$E$18+H30*'📊 Resumen Ejecutivo'!$E$19 -> 5159.5918
B31: TOTAL | C31: 18 días | D31: =SUM(D16:D30) -> 44875000 | E31: =SUM(E16:E30) -> 2526296.3 | F31: =SUM(F16:F30) -> 2127407.4 | G31: =SUM(G16:G30) -> 448750 | H31: =SUM(H16:H30) -> 2948928.6 | I31: =SUM(I16:I30) -> 8051382.3 | J31: =SUM(J16:J30) -> 136360.64
B33: * Celdas en amarillo (CPM, CTR, Frecuencia) son editables desde la hoja 'Resumen Ejecutivo' o directamente aquí.
